collective.mosaicpage-1.0.0a3-py3.11-nspkg.pth
collective/mosaicpage/__init__.py
collective/mosaicpage/configure.zcml
collective/mosaicpage/interfaces.py
collective/mosaicpage/messagefactory.py
collective/mosaicpage/patches.py
collective/mosaicpage/permissions.zcml
collective/mosaicpage/profiles.zcml
collective/mosaicpage/setuphandlers.py
collective/mosaicpage/testing.py
collective/mosaicpage/content/__init__.py
collective/mosaicpage/content/mosaic_page.py
collective/mosaicpage/layouts/manifest.cfg
collective/mosaicpage/layouts/mosaicpage.html
collective/mosaicpage/layouts/mosaicpage.png
collective/mosaicpage/locales/collective.mosaicpage.pot
collective/mosaicpage/locales/update.sh
collective/mosaicpage/locales/nl/LC_MESSAGES/collective.mosaicpage.mo
collective/mosaicpage/locales/nl/LC_MESSAGES/collective.mosaicpage.po
collective/mosaicpage/profiles/default/browserlayer.xml
collective/mosaicpage/profiles/default/metadata.xml
collective/mosaicpage/profiles/default/rolemap.xml
collective/mosaicpage/profiles/default/types.xml
collective/mosaicpage/profiles/default/registry/icons.xml
collective/mosaicpage/profiles/default/registry/main.xml
collective/mosaicpage/profiles/default/types/MosaicPage.xml
collective/mosaicpage/profiles/uninstall/browserlayer.xml
collective/mosaicpage/tests/__init__.py
collective/mosaicpage/tests/test_ct_mosaic_page.py
collective/mosaicpage/tests/test_setup.py
collective.mosaicpage-1.0.0a3.dist-info/LICENSE.GPL
collective.mosaicpage-1.0.0a3.dist-info/LICENSE.rst
collective.mosaicpage-1.0.0a3.dist-info/METADATA
collective.mosaicpage-1.0.0a3.dist-info/WHEEL
collective.mosaicpage-1.0.0a3.dist-info/entry_points.txt
collective.mosaicpage-1.0.0a3.dist-info/namespace_packages.txt
collective.mosaicpage-1.0.0a3.dist-info/top_level.txt
collective.mosaicpage-1.0.0a3.dist-info/RECORD
